setup.py
MellPlayer.egg-info/PKG-INFO
MellPlayer.egg-info/SOURCES.txt
MellPlayer.egg-info/dependency_links.txt
MellPlayer.egg-info/entry_points.txt
MellPlayer.egg-info/requires.txt
MellPlayer.egg-info/top_level.txt
mellplayer/__init__.py
mellplayer/api.py
mellplayer/controller.py
mellplayer/deco.py
mellplayer/directory.py
mellplayer/mell_logger.py
mellplayer/player.py
mellplayer/start.py
mellplayer/ui.py
mellplayer/watcher.py
mellplayer/event/__init__.py
mellplayer/event/ui_event.py
mellplayer/utils/__init__.py
mellplayer/utils/encrypt_utils.py
mellplayer/utils/getch.py
mellplayer/utils/mpv.py