Metadata-Version: 1.0
Name: MellPlayer
Version: 0.1.0
Summary: A tiny terminal player of NetEase-Music based on Python
Home-page: https://github.com/Mellcap/MellPlayer
Author: Mellcap
Author-email: imellcap@gmail.com
License: MIT
Keywords: mellplayer,terminal,netease,playlist,music,cli,player
Platform: UNKNOWN
